PyPAKParser/PyPAKParser.py
PyPAKParser/__init__.py
PyPAKParser-1.2.0.dist-info/LICENSE
PyPAKParser-1.2.0.dist-info/METADATA
PyPAKParser-1.2.0.dist-info/WHEEL
PyPAKParser-1.2.0.dist-info/top_level.txt
PyPAKParser-1.2.0.dist-info/RECORD
